online_store/__init__.py
online_store/__main__.py
online_store/order_management.py
online_store/user_management.py
onine_store_for_CU-0.1.dist-info/METADATA
onine_store_for_CU-0.1.dist-info/WHEEL
onine_store_for_CU-0.1.dist-info/top_level.txt
onine_store_for_CU-0.1.dist-info/RECORD
