Metadata-Version: 2.1
Name: onine_store_for_CU
Version: 0.1
Summary: Менджер товаров и учетных записей
Author-email: Ruslan <r.khuseyinov@edu.centraluniversity.ru>
License: MIT
Requires-Python: >=3.12
